ilds/__init__.py
ilds/cmd.py
ilds/everything.py
ilds/excel_xlrd.py
ilds/excel_xlsx.py
ilds/file.py
ilds/match_data.py
ilds/md.py
ilds/md5summer.py
ilds/mycsv.py
ilds/net.py
ilds/pd.py
ilds/spider.py
ilds/time.py
ilds/util.py
ilds/versions.py
ilds/django/__init__.py
ilds/django/admin.py
ilds/django/import_export.py
ilds/django/model.py
ilds/django/user.py
ilds/django/util.py
ilds/lib/__init__.py
ilds/lib/browsercookie.py
ilds/lib/hexdump.py
ilds/lib/configobj/__init__.py
ilds/lib/configobj/_version.py
ilds/lib/configobj/validate.py
ilds-2024.7.15.dist-info/LICENSE
ilds-2024.7.15.dist-info/METADATA
ilds-2024.7.15.dist-info/WHEEL
ilds-2024.7.15.dist-info/top_level.txt
ilds-2024.7.15.dist-info/RECORD
